setup.py
bambu_fileupload/__init__.py
bambu_fileupload/handlers.py
bambu_fileupload/models.py
bambu_fileupload/urls.py
bambu_fileupload/views.py
bambu_fileupload.egg-info/PKG-INFO
bambu_fileupload.egg-info/SOURCES.txt
bambu_fileupload.egg-info/dependency_links.txt
bambu_fileupload.egg-info/requires.txt
bambu_fileupload.egg-info/top_level.txt
bambu_fileupload/migrations/0001_initial.py
bambu_fileupload/migrations/__init__.py
bambu_fileupload/static/fileupload/css/bootstrap.css
bambu_fileupload/static/fileupload/img/loading.gif
bambu_fileupload/static/fileupload/img/progressbar.gif
bambu_fileupload/static/fileupload/img/filetypes/_blank.png
bambu_fileupload/static/fileupload/img/filetypes/aac.png
bambu_fileupload/static/fileupload/img/filetypes/ai.png
bambu_fileupload/static/fileupload/img/filetypes/aiff.png
bambu_fileupload/static/fileupload/img/filetypes/avi.png
bambu_fileupload/static/fileupload/img/filetypes/bmp.png
bambu_fileupload/static/fileupload/img/filetypes/c.png
bambu_fileupload/static/fileupload/img/filetypes/cpp.png
bambu_fileupload/static/fileupload/img/filetypes/css.png
bambu_fileupload/static/fileupload/img/filetypes/dat.png
bambu_fileupload/static/fileupload/img/filetypes/dmg.png
bambu_fileupload/static/fileupload/img/filetypes/doc.png
bambu_fileupload/static/fileupload/img/filetypes/dotx.png
bambu_fileupload/static/fileupload/img/filetypes/dwg.png
bambu_fileupload/static/fileupload/img/filetypes/dxf.png
bambu_fileupload/static/fileupload/img/filetypes/eps.png
bambu_fileupload/static/fileupload/img/filetypes/exe.png
bambu_fileupload/static/fileupload/img/filetypes/flv.png
bambu_fileupload/static/fileupload/img/filetypes/gif.png
bambu_fileupload/static/fileupload/img/filetypes/h.png
bambu_fileupload/static/fileupload/img/filetypes/hpp.png
bambu_fileupload/static/fileupload/img/filetypes/html.png
bambu_fileupload/static/fileupload/img/filetypes/ics.png
bambu_fileupload/static/fileupload/img/filetypes/iso.png
bambu_fileupload/static/fileupload/img/filetypes/java.png
bambu_fileupload/static/fileupload/img/filetypes/jpg.png
bambu_fileupload/static/fileupload/img/filetypes/js.png
bambu_fileupload/static/fileupload/img/filetypes/key.png
