Metadata-Version: 1.1
Name: bambu-fileupload
Version: 2.2
Summary: A wrapper around the jQuery.fileupload library
Home-page: http://pypi.python.org/pypi/bambu-fileupload
Author: Steadman
Author-email: mark@steadman.io
License: UNKNOWN
Platform: UNKNOWN
Classifier: Development Status :: 4 - Beta
Classifier: Environment :: Web Environment
Classifier: Framework :: Django
